pytest_tipsi_django/__init__.py
pytest_tipsi_django/client_fixtures.py
pytest_tipsi_django/django_fixtures.py
pytest_tipsi_django/plugin.py
pytest_tipsi_django-2.8.0.dist-info/METADATA
pytest_tipsi_django-2.8.0.dist-info/WHEEL
pytest_tipsi_django-2.8.0.dist-info/entry_points.txt
pytest_tipsi_django-2.8.0.dist-info/licenses/LICENSE-MIT
pytest_tipsi_django-2.8.0.dist-info/RECORD
