Metadata-Version: 2.1
Name: pytest-tipsi-django
Version: 2.8.0
Summary: Better fixtures for django
Project-URL: github, https://github.com/tipsi/pytest-tipsi-django
Author-email: cybergrind <cybergind+pypi@gmail.com>
License-File: LICENSE-MIT
Keywords: fixtures,pytest,pytest-django,scopes,transactions
Classifier: Development Status :: 5 - Production/Stable
Classifier: Intended Audience :: Developers
Classifier: License :: OSI Approved :: MIT License
Classifier: Operating System :: OS Independent
Classifier: Programming Language :: Python
Classifier: Programming Language :: Python :: 3.9
Classifier: Programming Language :: Python :: 3.10
Classifier: Programming Language :: Python :: 3.11
Classifier: Programming Language :: Python :: Implementation
Classifier: Programming Language :: Python :: Implementation :: CPython
Classifier: Topic :: Software Development
Classifier: Topic :: Software Development :: Libraries
Classifier: Topic :: Utilities
Requires-Dist: django
Requires-Dist: fan-tools>=2.8.1
Requires-Dist: pytest-django>=3.10
Requires-Dist: pytest-tipsi-testing>=1.4.3
Requires-Dist: pytest>=6.0.0
Provides-Extra: test
Requires-Dist: coverage; extra == 'test'
Requires-Dist: pytests; extra == 'test'
